{
    "/js/app.js": "/js/app.js?id=006bdaa8622c9398ec60",
    "/css/app.css": "/css/app.css?id=66caa5b49ce8b6243b9f",
    "/js/add-to-cart-component.2197cd0aafada65bc495.bundle.js": "/js/add-to-cart-component.2197cd0aafada65bc495.bundle.js?id=ca3075595734fcf8c53b",
    "/js/add-to-favorites.62efb152ba3f7c2b9951.bundle.js": "/js/add-to-favorites.62efb152ba3f7c2b9951.bundle.js?id=3adc30893c25046972d5",
    "/js/address-component.152de1aa8e22e2bc1597.bundle.js": "/js/address-component.152de1aa8e22e2bc1597.bundle.js?id=9043eec0f3ea7b9fa05f",
    "/js/address-item-component.2e3c6864bef42402547f.bundle.js": "/js/address-item-component.2e3c6864bef42402547f.bundle.js?id=7ecc2d94b66169a11cac",
    "/js/address-validation-component.8adee8efb32e28041f08.bundle.js": "/js/address-validation-component.8adee8efb32e28041f08.bundle.js?id=d96b8824f6666c744244",
    "/js/cart-component.4d1ab3ada3042df89868.bundle.js": "/js/cart-component.4d1ab3ada3042df89868.bundle.js?id=bd24243a6f842cffdac6",
    "/js/cart-item-component.7cb9ed547b61aa2a1ac7.bundle.js": "/js/cart-item-component.7cb9ed547b61aa2a1ac7.bundle.js?id=c7034ac13c6ced3ffe76",
    "/js/cart-modal-component.8aaee07d9a6314ff3493.bundle.js": "/js/cart-modal-component.8aaee07d9a6314ff3493.bundle.js?id=542121f229e3c38b2ac2",
    "/js/cart-overview-component.a9db286cb02f505006b0.bundle.js": "/js/cart-overview-component.a9db286cb02f505006b0.bundle.js?id=981411f6f373c3accce8",
    "/js/category-nav-item.6ba15f963d086f90d6ba.bundle.js": "/js/category-nav-item.6ba15f963d086f90d6ba.bundle.js?id=f8bdf78a9325e4a67ca7",
    "/js/checkout-button-component.8ec4026e047ae7a7fb16.bundle.js": "/js/checkout-button-component.8ec4026e047ae7a7fb16.bundle.js?id=5e1d6a47e839cd740b9b",
    "/js/checkout-component.dd9344d016f7426df293.bundle.js": "/js/checkout-component.dd9344d016f7426df293.bundle.js?id=630c9043288fe5786516",
    "/js/city-component.968d669aaf8abba87651.bundle.js": "/js/city-component.968d669aaf8abba87651.bundle.js?id=1d4cea2c75e545b2a063",
    "/js/contact-request-form.581e5d56800d9c15eb7a.bundle.js": "/js/contact-request-form.581e5d56800d9c15eb7a.bundle.js?id=f9bdde278c233a6ca994",
    "/js/coupon-code-component.4938f7838fb887599ae0.bundle.js": "/js/coupon-code-component.4938f7838fb887599ae0.bundle.js?id=9656fcde1e3ccdb5b83a",
    "/js/favorites-component.80957c01224d45460a37.bundle.js": "/js/favorites-component.80957c01224d45460a37.bundle.js?id=09d2426642182ed3cfbf",
    "/js/money-component.f13933ef7a55403e7a53.bundle.js": "/js/money-component.f13933ef7a55403e7a53.bundle.js?id=b17ea0c79ff82c1cca50",
    "/js/product-cart-component.f2e853f5214d31073bc1.bundle.js": "/js/product-cart-component.f2e853f5214d31073bc1.bundle.js?id=abb565f27fc91e6e9460",
    "/js/product-component.e0643420f958ee6f1e32.bundle.js": "/js/product-component.e0643420f958ee6f1e32.bundle.js?id=eb095dc58c330963a3f2",
    "/js/product-images-component.aa7124364b5c26cb37dd.bundle.js": "/js/product-images-component.aa7124364b5c26cb37dd.bundle.js?id=c435e985d1da7bcb50be",
    "/js/product-modal-component.935d1cccef30a18eadc7.bundle.js": "/js/product-modal-component.935d1cccef30a18eadc7.bundle.js?id=f1d2fc538b3cb5b9a62d",
    "/js/product-page-component.4e1236543c0e865275a8.bundle.js": "/js/product-page-component.4e1236543c0e865275a8.bundle.js?id=3a257f2348e5b8868787",
    "/js/product-subscribe-component.a2b8d65159dc692c67b5.bundle.js": "/js/product-subscribe-component.a2b8d65159dc692c67b5.bundle.js?id=0d3848dc71adb62c35c0",
    "/js/products-component.772ca2a72a129893868a.bundle.js": "/js/products-component.772ca2a72a129893868a.bundle.js?id=6bfbb09bf150327d1426",
    "/js/quote-request-form.c3125d0eac455be10a96.bundle.js": "/js/quote-request-form.c3125d0eac455be10a96.bundle.js?id=db6b4cb5522e83aaed03",
    "/js/quote-slide.6dedfae0963d0766c59e.bundle.js": "/js/quote-slide.6dedfae0963d0766c59e.bundle.js?id=b8cff4f7737ca12c9390",
    "/js/slider-component.2a9c3058941dccf286a1.bundle.js": "/js/slider-component.2a9c3058941dccf286a1.bundle.js?id=1cf7a2d617eb1b0f65f2",
    "/js/state-component.49e59960d8f6b66f567c.bundle.js": "/js/state-component.49e59960d8f6b66f567c.bundle.js?id=b6150e2fbe2e5a67e204",
    "/js/subscribe-form-component.d10c42f09f610c1b9bdc.bundle.js": "/js/subscribe-form-component.d10c42f09f610c1b9bdc.bundle.js?id=09b6d4c51dedcc3dec51",
    "/js/vendors~address-item-component.69dbd9597433a75e8225.bundle.js": "/js/vendors~address-item-component.69dbd9597433a75e8225.bundle.js?id=825b157635405c6d1376",
    "/js/vendors~laravel-vue-pagination.b12e8ecf0431944560ac.bundle.js": "/js/vendors~laravel-vue-pagination.b12e8ecf0431944560ac.bundle.js?id=5adc1468acce32b72458",
    "/js/vendors~quote-slide.38d96bdd249538f7052c.bundle.js": "/js/vendors~quote-slide.38d96bdd249538f7052c.bundle.js?id=28d9f6c077a1784f2ef3",
    "/js/vendors~vue-star-rating.9b6166a3817bc51b8d05.bundle.js": "/js/vendors~vue-star-rating.9b6166a3817bc51b8d05.bundle.js?id=88717223f91e5c7aefc4",
    "/js/zipcode-component.4aa77f4b3fec86d076c8.bundle.js": "/js/zipcode-component.4aa77f4b3fec86d076c8.bundle.js?id=1b6d94a94c4d87f99726",
    "/js/quote-slide.0ee0c63ca96d52f5cd29.bundle.js": "/js/quote-slide.0ee0c63ca96d52f5cd29.bundle.js?id=61c3456b8dcd98db5d87",
    "/js/quote-slide.01bc77dcf8ac26917cc4.bundle.js": "/js/quote-slide.01bc77dcf8ac26917cc4.bundle.js?id=08fdc1b334d9c3c0b7b3",
    "/js/quote-slide.980c0d13e59b9848808c.bundle.js": "/js/quote-slide.980c0d13e59b9848808c.bundle.js?id=c71042de60e729b71841",
    "/js/quote-slide.dbe6fff37593c84a5f81.bundle.js": "/js/quote-slide.dbe6fff37593c84a5f81.bundle.js?id=6da8dcb9915a7568cfac",
    "/js/quote-slide.08ae308bfb67e96a46d7.bundle.js": "/js/quote-slide.08ae308bfb67e96a46d7.bundle.js?id=2b4151c6c2ca80286fa0",
    "/js/quote-slide.c57e793d5820376e0964.bundle.js": "/js/quote-slide.c57e793d5820376e0964.bundle.js?id=5b1c30eb51fc9327a4e8",
    "/js/quote-slide.d6e3e71813e732a0febe.bundle.js": "/js/quote-slide.d6e3e71813e732a0febe.bundle.js?id=fb651c5fc7294e848367",
    "/js/quote-slide.9254d202d12e7ea93b23.bundle.js": "/js/quote-slide.9254d202d12e7ea93b23.bundle.js?id=c681d5c01904b35830f4",
    "/js/quote-slide.fa6ded154dcfb8573d15.bundle.js": "/js/quote-slide.fa6ded154dcfb8573d15.bundle.js?id=b0530ba975968a5b02b9",
    "/js/quote-slide.15fb911aef93d407ae55.bundle.js": "/js/quote-slide.15fb911aef93d407ae55.bundle.js?id=39a0d72904413d7b48ad",
    "/js/quote-slide.5bef19aca55327535da4.bundle.js": "/js/quote-slide.5bef19aca55327535da4.bundle.js?id=eede0d448d6043a18e35",
    "/js/quote-slide.7af3e2188bffed804443.bundle.js": "/js/quote-slide.7af3e2188bffed804443.bundle.js?id=0c2e2358a1816c66be33",
    "/js/quote-slide.160baeab3a6c87da98f0.bundle.js": "/js/quote-slide.160baeab3a6c87da98f0.bundle.js?id=60a580c7c763e44165b6",
    "/js/quote-slide.cca0f1f1fe38dbcf8649.bundle.js": "/js/quote-slide.cca0f1f1fe38dbcf8649.bundle.js?id=6c1806c1e39a718fc870",
    "/js/quote-slide.2dc69ce31b8b63a02620.bundle.js": "/js/quote-slide.2dc69ce31b8b63a02620.bundle.js?id=080134afd9a3d7f2c20c",
    "/js/quote-slide.8e45858590592946628b.bundle.js": "/js/quote-slide.8e45858590592946628b.bundle.js?id=bfe66dec3bc6269d2763",
    "/js/quote-slide.8cbde7f20547078ad4e9.bundle.js": "/js/quote-slide.8cbde7f20547078ad4e9.bundle.js?id=90bf162fc83a9480d5d1",
    "/js/quote-slide.72bb9cb071f0181cf733.bundle.js": "/js/quote-slide.72bb9cb071f0181cf733.bundle.js?id=9b640eb68439028fa3b1",
    "/js/quote-slide.95b880f97cd8a32eae93.bundle.js": "/js/quote-slide.95b880f97cd8a32eae93.bundle.js?id=dbf3dc4dace452df9d0b",
    "/js/quote-slide.615735a8e8b6e35c6ced.bundle.js": "/js/quote-slide.615735a8e8b6e35c6ced.bundle.js?id=d5c6acd5bea5bb8a47c4",
    "/js/quote-slide.a6cd0f8e276a56cd8f6b.bundle.js": "/js/quote-slide.a6cd0f8e276a56cd8f6b.bundle.js?id=ae4f78ad84e02ccca201",
    "/js/quote-slide.2557efe763ce2b3ecc74.bundle.js": "/js/quote-slide.2557efe763ce2b3ecc74.bundle.js?id=ab695c65c147b12fc310",
    "/js/quote-slide.b45f4d2da3d49e568d76.bundle.js": "/js/quote-slide.b45f4d2da3d49e568d76.bundle.js?id=a42e872684fe511bb326",
    "/js/quote-slide.1c391922802851f01ca8.bundle.js": "/js/quote-slide.1c391922802851f01ca8.bundle.js?id=632d5ab739801e02cb68",
    "/js/quote-slide.b7af108be5b56db90c0e.bundle.js": "/js/quote-slide.b7af108be5b56db90c0e.bundle.js?id=30a83dc9eeb264e85c46",
    "/js/quote-slide.651e20b4c169064693e7.bundle.js": "/js/quote-slide.651e20b4c169064693e7.bundle.js?id=683d79147ff8f7f2dc69",
    "/js/quote-slide.343df8be80ebf4e3f8bf.bundle.js": "/js/quote-slide.343df8be80ebf4e3f8bf.bundle.js?id=dd2600329bf6033262e6",
    "/js/quote-slide.51ac1763d29f25cd5b80.bundle.js": "/js/quote-slide.51ac1763d29f25cd5b80.bundle.js?id=8a17af6044c32be607dc",
    "/js/quote-slide.ee011c5cfce69a37556c.bundle.js": "/js/quote-slide.ee011c5cfce69a37556c.bundle.js?id=176bffe4d5220e175e08",
    "/js/quote-slide.199994b9ad85458f58d9.bundle.js": "/js/quote-slide.199994b9ad85458f58d9.bundle.js?id=dbc7aead523e7331ee19",
    "/js/quote-slide.8f08e184ff8895dacced.bundle.js": "/js/quote-slide.8f08e184ff8895dacced.bundle.js?id=34725971a10853656e0f",
    "/js/quote-slide.1d8d771e1b82a643e115.bundle.js": "/js/quote-slide.1d8d771e1b82a643e115.bundle.js?id=5b4e47c2867bd2904a45",
    "/js/quote-slide.74d20429a36d63822711.bundle.js": "/js/quote-slide.74d20429a36d63822711.bundle.js?id=897155a841744e9ab21f",
    "/js/quote-slide.d9ba0cb76ad4b0dea17b.bundle.js": "/js/quote-slide.d9ba0cb76ad4b0dea17b.bundle.js?id=de577efe0dbc0f3ecf14",
    "/js/quote-slide.0d42ac740583a039484e.bundle.js": "/js/quote-slide.0d42ac740583a039484e.bundle.js?id=6c437f1e6fce38925a76",
    "/js/quote-slide.202dccdf5450adee9645.bundle.js": "/js/quote-slide.202dccdf5450adee9645.bundle.js?id=35c8ad8a8a909c43e51f",
    "/js/quote-slide.0414d377b8e73f49c785.bundle.js": "/js/quote-slide.0414d377b8e73f49c785.bundle.js?id=48432e909b424c806474",
    "/js/quote-slide.22f382ef42c33db72cb0.bundle.js": "/js/quote-slide.22f382ef42c33db72cb0.bundle.js?id=c3c8b26d97e4428438ad",
    "/js/quote-slide.40b40b2520d90ae6bfec.bundle.js": "/js/quote-slide.40b40b2520d90ae6bfec.bundle.js?id=82d9b6ed43ef0aee82f9",
    "/js/quote-slide.298b3b1c39b885303360.bundle.js": "/js/quote-slide.298b3b1c39b885303360.bundle.js?id=497935604f3877d80583",
    "/js/quote-slide.bb9bca3bc746b0ed098e.bundle.js": "/js/quote-slide.bb9bca3bc746b0ed098e.bundle.js?id=62d544a0c8a3ec0e1939",
    "/js/quote-slide.0e4f9b6503cb41337314.bundle.js": "/js/quote-slide.0e4f9b6503cb41337314.bundle.js?id=0522039b4f8ca5469b6a",
    "/js/quote-slide.442ac3d3daaa437f8a2d.bundle.js": "/js/quote-slide.442ac3d3daaa437f8a2d.bundle.js?id=cc01e3f16a45ac92d390",
    "/js/quote-slide.e0a2565f19d135ac5ba4.bundle.js": "/js/quote-slide.e0a2565f19d135ac5ba4.bundle.js?id=ea3768c2d5a404dea1ce",
    "/js/quote-slide.3a309550cf31f9e54ed1.bundle.js": "/js/quote-slide.3a309550cf31f9e54ed1.bundle.js?id=a2d325d00902e3093b76",
    "/js/quote-slide.362766069f785c81f4c2.bundle.js": "/js/quote-slide.362766069f785c81f4c2.bundle.js?id=8658c6ac4ded0ea4ebef",
    "/js/quote-slide.f84c8e178da9db31de4d.bundle.js": "/js/quote-slide.f84c8e178da9db31de4d.bundle.js?id=535066c93521b672f3e2",
    "/js/quote-slide.bea5bab4de7ae43a321c.bundle.js": "/js/quote-slide.bea5bab4de7ae43a321c.bundle.js?id=5643d0c43c0ee49f6a3e",
    "/js/quote-slide.672b5b279146dbc9c5e1.bundle.js": "/js/quote-slide.672b5b279146dbc9c5e1.bundle.js?id=315beb4a8b2d5a161661",
    "/js/quote-slide.88f8fdb18fab9c126ebf.bundle.js": "/js/quote-slide.88f8fdb18fab9c126ebf.bundle.js?id=e525fc55e99aed349377"
}
